tgo_memory/__init__.py
tgo_memory/client.py
tgo_memory/exceptions.py
tgo_memory/models.py
tgo_memory/session.py
tgo_memory/sync_client.py
tgo_memory/utils.py
tgo_memory-1.0.0.dist-info/LICENSE
tgo_memory-1.0.0.dist-info/METADATA
tgo_memory-1.0.0.dist-info/WHEEL
tgo_memory-1.0.0.dist-info/RECORD
