Metadata-Version: 2.3
Name: tgo-memory
Version: 1.0.0
Summary: TGO-Memory Python SDK - 智能用户记忆管理系统的 Python 客户端
Keywords: memory,ai,llm,sdk,client
Author: TGO-Memory Team
Author-email: team@tgo.ai
Requires-Python: >=3.8.1,<4.0.0
Classifier: Development Status :: 3 - Alpha
Classifier: Intended Audience :: Developers
Classifier: License :: OSI Approved :: MIT License
Classifier: Programming Language :: Python :: 3
Classifier: Programming Language :: Python :: 3.9
Classifier: Programming Language :: Python :: 3.10
Classifier: Programming Language :: Python :: 3.11
Classifier: Programming Language :: Python :: 3.12
Classifier: Programming Language :: Python :: 3.13
Classifier: Programming Language :: Python :: 3.8
Classifier: Topic :: Scientific/Engineering :: Artificial Intelligence
Classifier: Topic :: Software Development :: Libraries :: Python Modules
Requires-Dist: httpx (>=0.25.0,<0.26.0)
Requires-Dist: pydantic (>=2.4.0,<3.0.0)
Requires-Dist: typing-extensions (>=4.8.0,<5.0.0)
Project-URL: Documentation, https://docs.tgo.ai
Project-URL: Homepage, https://github.com/tgoai/tgo-memory
Project-URL: Repository, https://github.com/tgoai/tgo-memory
